Metadata-Version: 1.0
Name: django-uuidfield
Version: 0.4.0
Summary: UUIDField in Django
Home-page: https://github.com/dcramer/django-uuidfield
Author: David Cramer
Author-email: dcramer@gmail.com
License: UNKNOWN
Platform: UNKNOWN
Classifier: Framework :: Django
Classifier: Intended Audience :: Developers
Classifier: Intended Audience :: System Administrators
Classifier: Operating System :: OS Independent
Classifier: Topic :: Software Development
